renn/__init__.py
renn/analysis_utils.py
renn/losses.py
renn/serialize.py
renn/utils.py
renn/version.py
renn/data/__init__.py
renn/data/data_utils.py
renn/data/datasets.py
renn/data/synthetic.py
renn/data/tokenizers.py
renn/data/wordpiece_tokenizer_learner_lib.py
renn/metaopt/__init__.py
renn/metaopt/api.py
renn/metaopt/common.py
renn/metaopt/losses.py
renn/metaopt/models.py
renn/metaopt/tasks.py
renn/metaopt/task_lib/__init__.py
renn/metaopt/task_lib/classification.py
renn/metaopt/task_lib/quadratic.py
renn/metaopt/task_lib/regression.py
renn/rnn/__init__.py
renn/rnn/cells.py
renn/rnn/fixed_points.py
renn/rnn/network.py
renn/rnn/unroll.py
renn-0.1.0.dist-info/LICENSE
renn-0.1.0.dist-info/METADATA
renn-0.1.0.dist-info/WHEEL
renn-0.1.0.dist-info/top_level.txt
renn-0.1.0.dist-info/RECORD
