Metadata-Version: 2.1
Name: renn
Version: 0.1.0
Summary: Research tools for Reverse Engineering Neural Networks (RENN).
Home-page: https://github.com/google-research/reverse-engineering-neural-networks
Author: Niru Maheswaranathan
Author-email: nirum@google.com
License: Apache-2.0
Platform: UNKNOWN
Requires-Python: >=3.7
Requires-Dist: numpy (>=1.12)
Requires-Dist: jax
Requires-Dist: jaxlib
Requires-Dist: msgpack
Requires-Dist: sklearn
Requires-Dist: tensorflow
Requires-Dist: tensorflow-text
Requires-Dist: tfds-nightly
Requires-Dist: tqdm
